streamlit_pollination/__init__.py
streamlit_pollination/dataframe.py
streamlit_pollination/interactors.py
streamlit_pollination/selectors.py
streamlit_pollination/api/__init__.py
streamlit_pollination/api/_base.py
streamlit_pollination/api/client.py
streamlit_pollination/api/jobs.py
streamlit_pollination/api/recipes.py
streamlit_pollination/api/runs.py
streamlit_pollination-0.1.0.dist-info/METADATA
streamlit_pollination-0.1.0.dist-info/WHEEL
streamlit_pollination-0.1.0.dist-info/top_level.txt
streamlit_pollination-0.1.0.dist-info/RECORD
