Metadata-Version: 2.1
Name: streamlit-pollination
Version: 0.1.0
Summary: A streamlit extention to interact with Pollination Cloud
Home-page: https://github.com/pollination/streamlit-pollination
Author: Ladybug Tools
Author-email: info@ladybug.tools
License: AGPL-3.0
Platform: UNKNOWN
Classifier: Programming Language :: Python :: 3.6
Classifier: Programming Language :: Python :: Implementation :: CPython
Classifier: License :: OSI Approved :: GNU Affero General Public License v3
Classifier: Operating System :: OS Independent
Requires-Dist: streamlit (>=1.1.0)
Requires-Dist: requests
Requires-Dist: queenbee
